Metadata-Version: 2.1
Name: kubefile
Version: 0.0.0
Summary: <description>
Home-page: https://github.com/marella/kubefile
Author: Ravindra Marella
License: MIT
Keywords: kubefile
Platform: UNKNOWN
Classifier: Development Status :: 1 - Planning
Classifier: Intended Audience :: Developers
Classifier: License :: OSI Approved :: MIT License
Classifier: Programming Language :: Python :: 3
Classifier: Topic :: Software Development
Classifier: Topic :: Software Development :: Libraries
Classifier: Topic :: Software Development :: Libraries :: Python Modules
